[{"Title":"Lord of The Rings","Year":1997,"Type":"Adventure","Poster":"https://media.moddb.com/cache/images/members/5/4550/4549205/thumb_620x2000/duck.jpg","reviews":[],"createdAt":"2022-05-21T13:46:57.112Z","imdbID":"2ar5wzkd5yl3fxcy55"},{"Title":"Lego Batman 3: Beyond Gotham","Year":"2014","Type":"game","Poster":"https://m.media-amazon.com/images/M/MV5BY2Q5YWY4YTEtYzBmOS00MzE3LTgwOTYtYTBmZTdiNjMzNDY5XkEyXkFqcGdeQXVyOTA1ODU0Mzc@._V1_SX300.jpg","imdbID":"tt3757728","reviews":[],"createdAt":"2022-05-21T14:47:14.846Z"},{"Title":"Lego Batman: Origins Vol. 3","Year":"2016","Type":"movie","Poster":"N/A","imdbID":"tt6728010","reviews":[],"createdAt":"2022-05-21T14:47:14.846Z"},{"Title":"Lego Batman: Dark Knight Vol. 3","Year":"2016","Type":"movie","Poster":"N/A","imdbID":"tt6728034","reviews":[],"createdAt":"2022-05-21T14:47:14.846Z"},{"Title":"Lego Batman: Arkham City Vol. 3","Year":"2017","Type":"movie","Poster":"N/A","imdbID":"tt7697464","reviews":[],"createdAt":"2022-05-21T14:47:14.846Z"},{"Title":"Lego Batman 3: Beyond Gotham","Year":"2014","Type":"game","Poster":"https://m.media-amazon.com/images/M/MV5BY2Q5YWY4YTEtYzBmOS00MzE3LTgwOTYtYTBmZTdiNjMzNDY5XkEyXkFqcGdeQXVyOTA1ODU0Mzc@._V1_SX300.jpg","imdbID":"tt3757728","reviews":[],"createdAt":"2022-05-21T14:49:16.324Z"},{"Title":"The Batman: Season 3 Unmasked","Year":"2007","Type":"movie","Poster":"https://m.media-amazon.com/images/M/MV5BMTIxNDg5MzMyMl5BMl5BanBnXkFtZTcwNDQwMDI0MQ@@._V1_SX300.jpg","imdbID":"tt3769348","reviews":[],"createdAt":"2022-05-21T14:49:16.324Z"},{"Title":"Lego Batman: Origins Vol. 3","Year":"2016","Type":"movie","Poster":"N/A","imdbID":"tt6728010","reviews":[],"createdAt":"2022-05-21T14:49:16.324Z"},{"Title":"Lego Batman: Dark Knight Vol. 3","Year":"2016","Type":"movie","Poster":"N/A","imdbID":"tt6728034","reviews":[],"createdAt":"2022-05-21T14:49:16.324Z"},{"Title":"Lego Batman: Arkham City Vol. 3","Year":"2017","Type":"movie","Poster":"N/A","imdbID":"tt7697464","reviews":[],"createdAt":"2022-05-21T14:49:16.324Z"},{"Title":"Titanic","Year":"1997","Type":"movie","Poster":"https://m.media-amazon.com/images/M/MV5BMDdmZGU3NDQtY2E5My00ZTliLWIzOTUtMTY4ZGI1YjdiNjk3XkEyXkFqcGdeQXVyNTA4NzY1MzY@._V1_SX300.jpg","imdbID":"tt0120338","reviews":[],"createdAt":"2022-05-21T15:04:35.255Z"},{"Title":"Titanic II","Year":"2010","Type":"movie","Poster":"https://m.media-amazon.com/images/M/MV5BMTMxMjQ1MjA5Ml5BMl5BanBnXkFtZTcwNjIzNjg1Mw@@._V1_SX300.jpg","imdbID":"tt1640571","reviews":[],"createdAt":"2022-05-21T15:04:35.255Z"},{"Title":"Titanic: The Legend Goes On...","Year":"2000","Type":"movie","Poster":"https://m.media-amazon.com/images/M/MV5BMTg5MjcxODAwMV5BMl5BanBnXkFtZTcwMTk4OTMwMg@@._V1_SX300.jpg","imdbID":"tt0330994","reviews":[],"createdAt":"2022-05-21T15:04:35.255Z"},{"Title":"Titanic","Year":"1953","Type":"movie","Poster":"https://m.media-amazon.com/images/M/MV5BMTU3NTUyMTc3Nl5BMl5BanBnXkFtZTgwOTA2MDE3MTE@._V1_SX300.jpg","imdbID":"tt0046435","reviews":[],"createdAt":"2022-05-21T15:04:35.255Z"},{"Title":"Raise the Titanic","Year":"1980","Type":"movie","Poster":"https://m.media-amazon.com/images/M/MV5BNTQyZGI0NDgtYTM0ZC00NTdkLTk2OTItYTgwYmYwNjZlNDRlXkEyXkFqcGdeQXVyMTY5Nzc4MDY@._V1_SX300.jpg","imdbID":"tt0081400","reviews":[],"createdAt":"2022-05-21T15:04:35.255Z"},{"Title":"Titanic","Year":"1996","Type":"series","Poster":"https://m.media-amazon.com/images/M/MV5BMTBhMjUzMDItYTBlZS00OThkLWJmZDQtMjg1YTQ5ZDkxYmFjXkEyXkFqcGdeQXVyNjk1Njg5NTA@._V1_SX300.jpg","imdbID":"tt0115392","reviews":[],"createdAt":"2022-05-21T15:04:35.255Z"},{"Title":"La leggenda del Titanic","Year":"1999","Type":"movie","Poster":"https://m.media-amazon.com/images/M/MV5BMjMxNDU5MTk1MV5BMl5BanBnXkFtZTgwMDk5NDUyMTE@._V1_SX300.jpg","imdbID":"tt1623780","reviews":[],"createdAt":"2022-05-21T15:04:35.255Z"},{"Title":"Titanic","Year":"2012","Type":"series","Poster":"https://m.media-amazon.com/images/M/MV5BMTA4MjIyZWEtZjYwMS00ZmQ1LWJiMDEtMWNiNTI5NWE3OGJjXkEyXkFqcGdeQXVyNjk1Njg5NTA@._V1_SX300.jpg","imdbID":"tt1869152","reviews":[],"createdAt":"2022-05-21T15:04:35.255Z"},{"Title":"Titanic: Blood and Steel","Year":"2012","Type":"series","Poster":"https://m.media-amazon.com/images/M/MV5BMjI2MzU2NzEzN15BMl5BanBnXkFtZTcwMzI5NTU3Nw@@._V1_SX300.jpg","imdbID":"tt1695366","reviews":[],"createdAt":"2022-05-21T15:04:35.255Z"},{"Title":"In Search of the Titanic","Year":"2004","Type":"movie","Poster":"https://m.media-amazon.com/images/M/MV5BNTYyM2FkZmYtZGEwMS00NDMwLWFhYTMtMDU4NzVhYzVmMDYyXkEyXkFqcGdeQXVyNjMwMjk0MTQ@._V1_SX300.jpg","imdbID":"tt1719665","reviews":[],"createdAt":"2022-05-21T15:04:35.255Z"},{"Title":"The Lord of the Rings: The Fellowship of the Ring","Year":"2001","Type":"movie","Poster":"https://m.media-amazon.com/images/M/MV5BN2EyZjM3NzUtNWUzMi00MTgxLWI0NTctMzY4M2VlOTdjZWRiXkEyXkFqcGdeQXVyNDUzOTQ5MjY@._V1_SX300.jpg","imdbID":"tt0120737","reviews":[],"createdAt":"2022-05-22T14:18:25.123Z"},{"Title":"The Lord of the Rings: The Return of the King","Year":"2003","Type":"movie","Poster":"https://m.media-amazon.com/images/M/MV5BNzA5ZDNlZWMtM2NhNS00NDJjLTk4NDItYTRmY2EwMWZlMTY3XkEyXkFqcGdeQXVyNzkwMjQ5NzM@._V1_SX300.jpg","imdbID":"tt0167260","reviews":[],"createdAt":"2022-05-22T14:18:25.123Z"},{"Title":"The Lord of the Rings: The Two Towers","Year":"2002","Type":"movie","Poster":"https://m.media-amazon.com/images/M/MV5BZGMxZTdjZmYtMmE2Ni00ZTdkLWI5NTgtNjlmMjBiNzU2MmI5XkEyXkFqcGdeQXVyNjU0OTQ0OTY@._V1_SX300.jpg","imdbID":"tt0167261","reviews":[],"createdAt":"2022-05-22T14:18:25.123Z"},{"Title":"The Lord of the Rings","Year":"1978","Type":"movie","Poster":"https://m.media-amazon.com/images/M/MV5BOGMyNWJhZmYtNGQxYi00Y2ZjLWJmNjktNTgzZWJjOTg4YjM3L2ltYWdlXkEyXkFqcGdeQXVyNTAyODkwOQ@@._V1_SX300.jpg","imdbID":"tt0077869","reviews":[],"createdAt":"2022-05-22T14:18:25.123Z"},{"Title":"The Lord of the Rings: The Two Towers","Year":"2002","Type":"game","Poster":"https://m.media-amazon.com/images/M/MV5BODI0Mzk3OTM4N15BMl5BanBnXkFtZTgwMTM4MTk4MDE@._V1_SX300.jpg","imdbID":"tt0347436","reviews":[],"createdAt":"2022-05-22T14:18:25.123Z"},{"Title":"The Lord of the Rings: The Return of the King","Year":"2003","Type":"game","Poster":"https://m.media-amazon.com/images/M/MV5BMjE5NTQwMTY5MV5BMl5BanBnXkFtZTgwODcwNjUwMTE@._V1_SX300.jpg","imdbID":"tt0387360","reviews":[],"createdAt":"2022-05-22T14:18:25.123Z"},{"Title":"The Lord of the Rings: The Battle for Middle-Earth","Year":"2004","Type":"game","Poster":"https://m.media-amazon.com/images/M/MV5BYWI5ODU0ZGEtYTA4YS00YzliLWJiZjEtYThkNTBkNTY1Y2FhXkEyXkFqcGdeQXVyNDAzNzA0MzE@._V1_SX300.jpg","imdbID":"tt0412935","reviews":[],"createdAt":"2022-05-22T14:18:25.123Z"},{"Title":"The Lord of the Rings: The Battle for Middle-Earth II","Year":"2006","Type":"game","Poster":"https://m.media-amazon.com/images/M/MV5BZTFlNTg5NzgtZmUyNS00MWJjLWFmNDktZmNiODEzZWY2YjgwXkEyXkFqcGdeQXVyNDAzNzA0MzE@._V1_SX300.jpg","imdbID":"tt0760172","reviews":[],"createdAt":"2022-05-22T14:18:25.123Z"},{"Title":"The Lord of the Rings: The Battle for Middle-earth II - The Rise of the Witch-king","Year":"2006","Type":"game","Poster":"https://m.media-amazon.com/images/M/MV5BMjYwMDIxNjg3MV5BMl5BanBnXkFtZTgwMTk5MTE4MDE@._V1_SX300.jpg","imdbID":"tt1058040","reviews":[],"createdAt":"2022-05-22T14:18:25.123Z"},{"Title":"The Lord of the Rings: The Third Age","Year":"2004","Type":"game","Poster":"https://m.media-amazon.com/images/M/MV5BMTMwMzM2NzU1M15BMl5BanBnXkFtZTcwOTQ3MzcyMQ@@._V1_SX300.jpg","imdbID":"tt0415947","reviews":[],"createdAt":"2022-05-22T14:18:25.123Z"},{"Title":"Tarzan","Year":"1999","Type":"movie","Poster":"https://m.media-amazon.com/images/M/MV5BY2ZiYWUxN2ItYmQxZi00NDlkLWE2NDAtOTNmYTg1MDI0NDk1XkEyXkFqcGdeQXVyNjUwNzk3NDc@._V1_SX300.jpg","imdbID":"tt0120855","reviews":[],"createdAt":"2022-05-22T14:18:41.284Z"},{"Title":"The Legend of Tarzan","Year":"2016","Type":"movie","Poster":"https://m.media-amazon.com/images/M/MV5BMzY3OTI0OTcyMF5BMl5BanBnXkFtZTgwNjkxNTAwOTE@._V1_SX300.jpg","imdbID":"tt0918940","reviews":[],"createdAt":"2022-05-22T14:18:41.284Z"},{"Title":"Greystoke: The Legend of Tarzan, Lord of the Apes","Year":"1984","Type":"movie","Poster":"https://m.media-amazon.com/images/M/MV5BM2NmYjZjOGItYTQ0ZC00YjcyLTk3MWUtYzdmZjY1MGNkMDViXkEyXkFqcGdeQXVyNzc5MjA3OA@@._V1_SX300.jpg","imdbID":"tt0087365","reviews":[],"createdAt":"2022-05-22T14:18:41.284Z"},{"Title":"Tarzan","Year":"2013","Type":"movie","Poster":"https://m.media-amazon.com/images/M/MV5BMTQyODEwMTM2Nl5BMl5BanBnXkFtZTgwMTg1MTA3MDE@._V1_SX300.jpg","imdbID":"tt1705952","reviews":[],"createdAt":"2022-05-22T14:18:41.284Z"},{"Title":"Tarzan 2: The Legend Begins","Year":"2005","Type":"movie","Poster":"https://m.media-amazon.com/images/M/MV5BODUwZWRkMzAtYzFhMS00MGU5LWJhNDQtNzI2NGQ1NDA3NTBiXkEyXkFqcGdeQXVyODc5NjY4MzU@._V1_SX300.jpg","imdbID":"tt0437503","reviews":[],"createdAt":"2022-05-22T14:18:41.284Z"},{"Title":"Tarzan the Ape Man","Year":"1932","Type":"movie","Poster":"https://m.media-amazon.com/images/M/MV5BNTVlMDAwMDQtMTEzMC00YjhlLWEyYTctNjMzN2M0NGI0MTEwXkEyXkFqcGdeQXVyNDE5MTU2MDE@._V1_SX300.jpg","imdbID":"tt0023551","reviews":[],"createdAt":"2022-05-22T14:18:41.284Z"},{"Title":"Tarzan & Jane","Year":"2002","Type":"movie","Poster":"https://m.media-amazon.com/images/M/MV5BMjAwMTM5NzM4OF5BMl5BanBnXkFtZTcwOTE2NDkyMQ@@._V1_SX300.jpg","imdbID":"tt0313680","reviews":[],"createdAt":"2022-05-22T14:18:41.284Z"},{"Title":"Tarzan the Ape Man","Year":"1981","Type":"movie","Poster":"https://m.media-amazon.com/images/M/MV5BZGU5ZTUyZmMtZjExYy00MDAzLTljZTEtMGE0MWI5YWFiYTJkXkEyXkFqcGdeQXVyNzc5MjA3OA@@._V1_SX300.jpg","imdbID":"tt0083170","reviews":[],"createdAt":"2022-05-22T14:18:41.284Z"},{"Title":"Tarzan and His Mate","Year":"1934","Type":"movie","Poster":"https://m.media-amazon.com/images/M/MV5BNmQ4OWJhY2MtNWUzZi00YjcwLThhNmEtMWU0YWQzNDEzNDcxXkEyXkFqcGdeQXVyNDE5MTU2MDE@._V1_SX300.jpg","imdbID":"tt0025862","reviews":[],"createdAt":"2022-05-22T14:18:41.284Z"},{"Title":"Tarzan Finds a Son!","Year":"1939","Type":"movie","Poster":"https://m.media-amazon.com/images/M/MV5BMGU5MDdhYzktYjUyNi00YjYyLThjNDMtNjRjYmE4NjJlNzYwXkEyXkFqcGdeQXVyNDE5MTU2MDE@._V1_SX300.jpg","imdbID":"tt0032007","reviews":[],"createdAt":"2022-05-22T14:18:41.284Z"},{"Title":"The Hobbit: An Unexpected Journey","Year":"2012","Type":"movie","Poster":"https://m.media-amazon.com/images/M/MV5BMTcwNTE4MTUxMl5BMl5BanBnXkFtZTcwMDIyODM4OA@@._V1_SX300.jpg","imdbID":"tt0903624","reviews":[],"createdAt":"2022-05-22T14:18:53.165Z"},{"Title":"The Hobbit: The Desolation of Smaug","Year":"2013","Type":"movie","Poster":"https://m.media-amazon.com/images/M/MV5BMzU0NDY0NDEzNV5BMl5BanBnXkFtZTgwOTIxNDU1MDE@._V1_SX300.jpg","imdbID":"tt1170358","reviews":[],"createdAt":"2022-05-22T14:18:53.165Z"},{"Title":"The Hobbit: The Battle of the Five Armies","Year":"2014","Type":"movie","Poster":"https://m.media-amazon.com/images/M/MV5BMTYzNDE3OTQ3MF5BMl5BanBnXkFtZTgwODczMTg4MjE@._V1_SX300.jpg","imdbID":"tt2310332","reviews":[],"createdAt":"2022-05-22T14:18:53.165Z"},{"Title":"The Hobbit","Year":"1977","Type":"movie","Poster":"https://m.media-amazon.com/images/M/MV5BNmNjZjEyZTgtM2M4Mi00OTQwLTliMTctYjNhOGNkNmFjZDM4XkEyXkFqcGdeQXVyNTc4Njg5MjA@._V1_SX300.jpg","imdbID":"tt0077687","reviews":[],"createdAt":"2022-05-22T14:18:53.165Z"},{"Title":"Lego the Hobbit: The Video Game","Year":"2014","Type":"game","Poster":"https://m.media-amazon.com/images/M/MV5BZDViNzE1YjQtZGNmNS00NzgzLWJiNTAtYjQzYTYxNWY5ODI3XkEyXkFqcGdeQXVyNDQ2OTk4MzI@._V1_SX300.jpg","imdbID":"tt3584562","reviews":[],"createdAt":"2022-05-22T14:18:53.165Z"},{"Title":"The Hobbit","Year":"1966","Type":"movie","Poster":"https://m.media-amazon.com/images/M/MV5BNTc3NjUxNzUtZTRlZC00YzAzLWI5NjItNDFkMzNjODc2ODg4XkEyXkFqcGdeQXVyMTA0MTM5NjI2._V1_SX300.jpg","imdbID":"tt1686804","reviews":[],"createdAt":"2022-05-22T14:18:53.165Z"},{"Title":"The Hobbit","Year":"2003","Type":"game","Poster":"https://m.media-amazon.com/images/M/MV5BZmQyMDBlMjAtMTU2My00ZjBkLWIyNzYtZWIwZjY1Y2ZlYjQxXkEyXkFqcGdeQXVyOTQxNzM2MjY@._V1_SX300.jpg","imdbID":"tt0395578","reviews":[],"createdAt":"2022-05-22T14:18:53.165Z"},{"Title":"A Day in the Life of a Hobbit","Year":"2002","Type":"movie","Poster":"https://m.media-amazon.com/images/M/MV5BMTk3ODI5Nzk4Nl5BMl5BanBnXkFtZTcwMDE5MTcyMQ@@._V1_SX300.jpg","imdbID":"tt0473467","reviews":[],"createdAt":"2022-05-22T14:18:53.165Z"},{"Title":"The Hobbit: The Swedolation of Smaug","Year":"2014","Type":"movie","Poster":"https://m.media-amazon.com/images/M/MV5BMzQxMTkyYmQtMWZmYi00NzJmLTg3MDItZmEyZDQ3NmE5OWE4XkEyXkFqcGdeQXVyMjMyNTkxNzY@._V1_SX300.jpg","imdbID":"tt4171362","reviews":[],"createdAt":"2022-05-22T14:18:53.165Z"},{"Title":"Secrets of Middle-Earth: Inside Tolkien's 'The Hobbit'","Year":"2003","Type":"movie","Poster":"https://m.media-amazon.com/images/M/MV5BMTc4MzUxMDU3Nl5BMl5BanBnXkFtZTcwNjYxMzQyMQ@@._V1_SX300.jpg","imdbID":"tt0401776","reviews":[],"createdAt":"2022-05-22T14:18:53.165Z"},{"Title":"The Dude in Me","Year":"2019","Type":"movie","Poster":"https://m.media-amazon.com/images/M/MV5BNmUxOTAxNzItYmM5OC00OTc4LWFmZDAtZTRkNmQ5YWU0MjNlXkEyXkFqcGdeQXVyNzI1NzMxNzM@._V1_SX300.jpg","imdbID":"tt9759978","reviews":[],"createdAt":"2022-05-22T14:19:00.855Z"},{"Title":"The Healing Powers of Dude","Year":"2020","Type":"series","Poster":"https://m.media-amazon.com/images/M/MV5BNGU0NTdmMGYtNTcyZi00NGE1LWI0MWYtOGEwZmQwNjA4YWRlXkEyXkFqcGdeQXVyMTMxODk2OTU@._V1_SX300.jpg","imdbID":"tt10540562","reviews":[],"createdAt":"2022-05-22T14:19:00.855Z"},{"Title":"The Dude Perfect Show","Year":"2016–2019","Type":"series","Poster":"https://m.media-amazon.com/images/M/MV5BNDZiMTI1YjEtYWNmMS00Mjg4LWE5MTItNGFlNGRjMWU4YjFkXkEyXkFqcGdeQXVyNzU5NzQyNjM@._V1_SX300.jpg","imdbID":"tt5512420","reviews":[],"createdAt":"2022-05-22T14:19:00.855Z"},{"Title":"The Dude Goes West","Year":"1948","Type":"movie","Poster":"https://m.media-amazon.com/images/M/MV5BNTE4NjRiZWItYjE0Yi00MDc0LThhYWQtMjdhOGIyNWE1OTA4XkEyXkFqcGdeQXVyMTMxMTY0OTQ@._V1_SX300.jpg","imdbID":"tt0040305","reviews":[],"createdAt":"2022-05-22T14:19:00.855Z"},{"Title":"The Dude Ranger","Year":"1934","Type":"movie","Poster":"https://m.media-amazon.com/images/M/MV5BYzk4YjY2MDYtMzZkOS00OWMwLWE2ZjgtY2Y2MWVkYjE1ZGMwL2ltYWdlL2ltYWdlXkEyXkFqcGdeQXVyMDMxMjQwMw@@._V1_SX300.jpg","imdbID":"tt0025073","reviews":[],"createdAt":"2022-05-22T14:19:00.855Z"},{"Title":"The Dude Bandit","Year":"1933","Type":"movie","Poster":"https://m.media-amazon.com/images/M/MV5BMTFiOTY2MjItZDFmOC00ZTQ5LTgyODUtOGJjYjJjYjc0ODg3L2ltYWdlXkEyXkFqcGdeQXVyNzEyMjEzNzc@._V1_SX300.jpg","imdbID":"tt0023970","reviews":[],"createdAt":"2022-05-22T14:19:00.855Z"},{"Title":"Buster Brown and the Dude","Year":"1904","Type":"movie","Poster":"N/A","imdbID":"tt1080559","reviews":[],"createdAt":"2022-05-22T14:19:00.855Z"},{"Title":"The Dude and the Burglars","Year":"1903","Type":"movie","Poster":"N/A","imdbID":"tt0445338","reviews":[],"createdAt":"2022-05-22T14:19:00.855Z"},{"Title":"Pizza Man vs. the Dude","Year":"2004","Type":"movie","Poster":"https://m.media-amazon.com/images/M/MV5BZTVmMTJkZmEtOTY1MS00ZTYzLTlhMjItNjliNmRiZTMxMjRjXkEyXkFqcGdeQXVyODkzMjUyNTg@._V1_SX300.jpg","imdbID":"tt0419062","reviews":[],"createdAt":"2022-05-22T14:19:00.855Z"},{"Title":"The Dude","Year":"2011","Type":"movie","Poster":"N/A","imdbID":"tt1939758","reviews":[],"createdAt":"2022-05-22T14:19:00.855Z"},{"Title":"Dune","Year":"2021","Type":"movie","Poster":"https://m.media-amazon.com/images/M/MV5BN2FjNmEyNWMtYzM0ZS00NjIyLTg5YzYtYThlMGVjNzE1OGViXkEyXkFqcGdeQXVyMTkxNjUyNQ@@._V1_SX300.jpg","imdbID":"tt1160419","reviews":[],"createdAt":"2022-05-22T14:19:09.565Z"},{"Title":"Dune","Year":"1984","Type":"movie","Poster":"https://m.media-amazon.com/images/M/MV5BYTAzYzNlMDMtMGRjYS00M2UxLTk0MmEtYmE4YWZiYmEwOTIwL2ltYWdlL2ltYWdlXkEyXkFqcGdeQXVyNzc5MjA3OA@@._V1_SX300.jpg","imdbID":"tt0087182","reviews":[],"createdAt":"2022-05-22T14:19:09.565Z"},{"Title":"Jodorowsky's Dune","Year":"2013","Type":"movie","Poster":"https://m.media-amazon.com/images/M/MV5BMTU0MzcxMTAxMl5BMl5BanBnXkFtZTgwODMyMTIxMTE@._V1_SX300.jpg","imdbID":"tt1935156","reviews":[],"createdAt":"2022-05-22T14:19:09.565Z"},{"Title":"Dune","Year":"2000","Type":"series","Poster":"https://m.media-amazon.com/images/M/MV5BMTU4MjMyMTkxN15BMl5BanBnXkFtZTYwODA5OTU5._V1_SX300.jpg","imdbID":"tt0142032","reviews":[],"createdAt":"2022-05-22T14:19:09.565Z"},{"Title":"Children of Dune","Year":"2003","Type":"series","Poster":"https://m.media-amazon.com/images/M/MV5BMTI3ODIwMTQ5OF5BMl5BanBnXkFtZTYwNTkwNDk5._V1_SX300.jpg","imdbID":"tt0287839","reviews":[],"createdAt":"2022-05-22T14:19:09.565Z"},{"Title":"Dune Drifter","Year":"2020","Type":"movie","Poster":"https://m.media-amazon.com/images/M/MV5BMjc4ODFiNzItZWY5OS00YzZkLWE0ZmYtMDYwODZlMDY0NjhhXkEyXkFqcGdeQXVyMDA4NzMyOA@@._V1_SX300.jpg","imdbID":"tt11835714","reviews":[],"createdAt":"2022-05-22T14:19:09.565Z"},{"Title":"Planet Dune","Year":"2021","Type":"movie","Poster":"https://m.media-amazon.com/images/M/MV5BYzVkNjZlMDctODEzMy00MWE1LWI4YTUtZjdmNDZhYmZhODI0XkEyXkFqcGdeQXVyNTkzMzg3NDM@._V1_SX300.jpg","imdbID":"tt15331462","reviews":[],"createdAt":"2022-05-22T14:19:09.565Z"},{"Title":"Dune Warriors","Year":"1991","Type":"movie","Poster":"https://m.media-amazon.com/images/M/MV5BNjU4NDc4ZTQtZGI1Ny00NTc4LTk4ODctOTIyZTliZmM0MmJjXkEyXkFqcGdeQXVyNjExODE1MDc@._V1_SX300.jpg","imdbID":"tt0099474","reviews":[],"createdAt":"2022-05-22T14:19:09.565Z"},{"Title":"Dune World","Year":"2021","Type":"movie","Poster":"https://m.media-amazon.com/images/M/MV5BMzMxMzQ4MTMtYTk4MC00Njc3LTllN2MtOThjMzg4OTgwNDNhXkEyXkFqcGdeQXVyMjc0Nzk1Mg@@._V1_SX300.jpg","imdbID":"tt14450978","reviews":[],"createdAt":"2022-05-22T14:19:09.565Z"},{"Title":"The Dune","Year":"2013","Type":"movie","Poster":"https://m.media-amazon.com/images/M/MV5BNzY4MWNkOTctMTM3NS00ZjE5LWIwNzMtOGIyMjY2YWVhNGE2XkEyXkFqcGdeQXVyMzU0NzkwMDg@._V1_SX300.jpg","imdbID":"tt2251648","reviews":[],"createdAt":"2022-05-22T14:19:09.566Z"},{"Title":"Harry Potter and the Deathly Hallows: Part 2","Year":"2011","Type":"movie","Poster":"https://m.media-amazon.com/images/M/MV5BMGVmMWNiMDktYjQ0Mi00MWIxLTk0N2UtN2ZlYTdkN2IzNDNlXkEyXkFqcGdeQXVyODE5NzE3OTE@._V1_SX300.jpg","imdbID":"tt1201607","reviews":[],"createdAt":"2022-05-22T14:19:23.591Z"},{"Title":"Harry Potter and the Sorcerer's Stone","Year":"2001","Type":"movie","Poster":"https://m.media-amazon.com/images/M/MV5BNjQ3NWNlNmQtMTE5ZS00MDdmLTlkZjUtZTBlM2UxMGFiMTU3XkEyXkFqcGdeQXVyNjUwNzk3NDc@._V1_SX300.jpg","imdbID":"tt0241527","reviews":[],"createdAt":"2022-05-22T14:19:23.591Z"},{"Title":"Harry Potter and the Chamber of Secrets","Year":"2002","Type":"movie","Poster":"https://m.media-amazon.com/images/M/MV5BMTcxODgwMDkxNV5BMl5BanBnXkFtZTYwMDk2MDg3._V1_SX300.jpg","imdbID":"tt0295297","reviews":[],"createdAt":"2022-05-22T14:19:23.591Z"},{"Title":"Harry Potter and the Prisoner of Azkaban","Year":"2004","Type":"movie","Poster":"https://m.media-amazon.com/images/M/MV5BMTY4NTIwODg0N15BMl5BanBnXkFtZTcwOTc0MjEzMw@@._V1_SX300.jpg","imdbID":"tt0304141","reviews":[],"createdAt":"2022-05-22T14:19:23.591Z"},{"Title":"Harry Potter and the Goblet of Fire","Year":"2005","Type":"movie","Poster":"https://m.media-amazon.com/images/M/MV5BMTI1NDMyMjExOF5BMl5BanBnXkFtZTcwOTc4MjQzMQ@@._V1_SX300.jpg","imdbID":"tt0330373","reviews":[],"createdAt":"2022-05-22T14:19:23.591Z"},{"Title":"Harry Potter and the Order of the Phoenix","Year":"2007","Type":"movie","Poster":"https://m.media-amazon.com/images/M/MV5BMTM0NTczMTUzOV5BMl5BanBnXkFtZTYwMzIxNTg3._V1_SX300.jpg","imdbID":"tt0373889","reviews":[],"createdAt":"2022-05-22T14:19:23.591Z"},{"Title":"Harry Potter and the Deathly Hallows: Part 1","Year":"2010","Type":"movie","Poster":"https://m.media-amazon.com/images/M/MV5BMTQ2OTE1Mjk0N15BMl5BanBnXkFtZTcwODE3MDAwNA@@._V1_SX300.jpg","imdbID":"tt0926084","reviews":[],"createdAt":"2022-05-22T14:19:23.591Z"},{"Title":"Harry Potter and the Half-Blood Prince","Year":"2009","Type":"movie","Poster":"https://m.media-amazon.com/images/M/MV5BNzU3NDg4NTAyNV5BMl5BanBnXkFtZTcwOTg2ODg1Mg@@._V1_SX300.jpg","imdbID":"tt0417741","reviews":[],"createdAt":"2022-05-22T14:19:23.591Z"},{"Title":"Harry Potter 20th Anniversary: Return to Hogwarts","Year":"2022","Type":"movie","Poster":"https://m.media-amazon.com/images/M/MV5BNTZkNWEyZTgtYzJlOS00OWNiLTgwZjMtZGU5NTRhNDNjOTRhXkEyXkFqcGdeQXVyNjk1Njg5NTA@._V1_SX300.jpg","imdbID":"tt16116174","reviews":[],"createdAt":"2022-05-22T14:19:23.591Z"},{"Title":"Harry Potter and the Forbidden Journey","Year":"2010","Type":"movie","Poster":"https://m.media-amazon.com/images/M/MV5BNDM0YzMyNGUtMTU1Yy00OTE2LWE5NzYtZDZhMTBmN2RkNjg3XkEyXkFqcGdeQXVyMzU5NjU1MDA@._V1_SX300.jpg","imdbID":"tt1756545","reviews":[],"createdAt":"2022-05-22T14:19:23.591Z"},{"Title":"Batman v Superman: Dawn of Justice","Year":"2016","Type":"movie","Poster":"https://m.media-amazon.com/images/M/MV5BYThjYzcyYzItNTVjNy00NDk0LTgwMWQtYjMwNmNlNWJhMzMyXkEyXkFqcGdeQXVyMTQxNzMzNDI@._V1_SX300.jpg","imdbID":"tt2975590","reviews":[],"createdAt":"2022-05-23T13:53:14.897Z"},{"Title":"Superman Returns","Year":"2006","Type":"movie","Poster":"https://m.media-amazon.com/images/M/MV5BNzY2ZDQ2MTctYzlhOC00MWJhLTgxMmItMDgzNDQwMDdhOWI2XkEyXkFqcGdeQXVyNjc1NTYyMjg@._V1_SX300.jpg","imdbID":"tt0348150","reviews":[],"createdAt":"2022-05-23T13:53:14.897Z"},{"Title":"Superman","Year":"1978","Type":"movie","Poster":"https://m.media-amazon.com/images/M/MV5BMzA0YWMwMTUtMTVhNC00NjRkLWE2ZTgtOWEzNjJhYzNiMTlkXkEyXkFqcGdeQXVyNjc1NTYyMjg@._V1_SX300.jpg","imdbID":"tt0078346","reviews":[],"createdAt":"2022-05-23T13:53:14.897Z"},{"Title":"Superman II","Year":"1980","Type":"movie","Poster":"https://m.media-amazon.com/images/M/MV5BODk2NjgzNTEtYzZhZC00ZTBkLTllMGQtMmMxMzU1NDRkM2RlXkEyXkFqcGdeQXVyNjc1NTYyMjg@._V1_SX300.jpg","imdbID":"tt0081573","reviews":[],"createdAt":"2022-05-23T13:53:14.897Z"},{"Title":"Superman III","Year":"1983","Type":"movie","Poster":"https://m.media-amazon.com/images/M/MV5BMzI3ZDllMTctNmI2Mi00OGQ4LTk2ZTQtYTJhMjA5ZGI2YmRkXkEyXkFqcGdeQXVyNjUwNzk3NDc@._V1_SX300.jpg","imdbID":"tt0086393","reviews":[],"createdAt":"2022-05-23T13:53:14.897Z"},{"Title":"Superman IV: The Quest for Peace","Year":"1987","Type":"movie","Poster":"https://m.media-amazon.com/images/M/MV5BMmIwZWY1YTYtNDlhOS00NDRmLWI4MzItNjk2NDc1N2NhYzNlXkEyXkFqcGdeQXVyNTUyMzE4Mzg@._V1_SX300.jpg","imdbID":"tt0094074","reviews":[],"createdAt":"2022-05-23T13:53:14.897Z"},{"Title":"Batman v Superman: Dawn of Justice Ultimate Edition","Year":"2016","Type":"movie","Poster":"https://m.media-amazon.com/images/M/MV5BYzgyMTMzZjUtNGNjMy00NTJjLWIzNDYtMTc2YzQwOGE5MGM4XkEyXkFqcGdeQXVyMTUwODYzMjcw._V1_SX300.jpg","imdbID":"tt18689424","reviews":[],"createdAt":"2022-05-23T13:53:14.897Z"},{"Title":"Superman & Lois","Year":"2021–","Type":"series","Poster":"https://m.media-amazon.com/images/M/MV5BOGYyMmViMjgtZjViZi00NjkzLThjZGItMzZhYmZmOWZlMzdhXkEyXkFqcGdeQXVyMTkxNjUyNQ@@._V1_SX300.jpg","imdbID":"tt11192306","reviews":[],"createdAt":"2022-05-23T13:53:14.897Z"},{"Title":"Superman/Batman: Apocalypse","Year":"2010","Type":"movie","Poster":"https://m.media-amazon.com/images/M/MV5BMjk3ODhmNjgtZjllOC00ZWZjLTkwYzQtNzc1Y2ZhMjY2ODE0XkEyXkFqcGdeQXVyNTAyODkwOQ@@._V1_SX300.jpg","imdbID":"tt1673430","reviews":[],"createdAt":"2022-05-23T13:53:14.897Z"},{"Title":"Lois & Clark: The New Adventures of Superman","Year":"1993–1997","Type":"series","Poster":"https://m.media-amazon.com/images/M/MV5BZTU1ZGFjNzEtZWYzZC00ZmI0LTg2NmMtN2YyNTY4YzhlODIyXkEyXkFqcGdeQXVyMjExMjk0ODk@._V1_SX300.jpg","imdbID":"tt0106057","reviews":[],"createdAt":"2022-05-23T13:53:14.897Z"},{"Title":"The Sound of Music","Year":"1965","Type":"movie","Poster":"https://m.media-amazon.com/images/M/MV5BODIxNjhkYjEtYzUyMi00YTNjLWE1YjktNjAyY2I2MWNkNmNmL2ltYWdlL2ltYWdlXkEyXkFqcGdeQXVyMTQxNzMzNDI@._V1_SX300.jpg","imdbID":"tt0059742","reviews":[],"createdAt":"2022-05-23T13:53:47.042Z"},{"Title":"The Sound of Music Live!","Year":"2013","Type":"movie","Poster":"https://m.media-amazon.com/images/M/MV5BMTUxOTI1MzMzMl5BMl5BanBnXkFtZTgwOTMzNjg2MDE@._V1_SX300.jpg","imdbID":"tt3141866","reviews":[],"createdAt":"2022-05-23T13:53:47.042Z"},{"Title":"The Sound of Music Live","Year":"2015","Type":"movie","Poster":"https://m.media-amazon.com/images/M/MV5BNzQ3YjM2YzYtMWU5My00MDY5LTkzYzgtZjM3NDY0ZTk1MGFiXkEyXkFqcGdeQXVyMjExMjk0ODk@._V1_SX300.jpg","imdbID":"tt5285494","reviews":[],"createdAt":"2022-05-23T13:53:47.042Z"},{"Title":"Creating the World of Harry Potter, Part 4: Sound and Music","Year":"2010","Type":"movie","Poster":"https://m.media-amazon.com/images/M/MV5BYjdhMWFhMjUtZWQ3ZC00OTNjLWI2MTgtYmU2ODMzNDgxMmViXkEyXkFqcGdeQXVyMjk2MTQxMzg@._V1_SX300.jpg","imdbID":"tt1781796","reviews":[],"createdAt":"2022-05-23T13:53:47.042Z"},{"Title":"The Bond Sound: The Music of 007","Year":"2000","Type":"movie","Poster":"https://m.media-amazon.com/images/M/MV5BYThlNzM2MmMtNDk0MC00YzM5LTgxZjEtZTMzMmI1ODQ0NDczL2ltYWdlL2ltYWdlXkEyXkFqcGdeQXVyMTQxMjk0Mg@@._V1_SX300.jpg","imdbID":"tt0307198","reviews":[],"createdAt":"2022-05-23T13:53:47.042Z"},{"Title":"The Sound of Music","Year":"1994","Type":"movie","Poster":"https://m.media-amazon.com/images/M/MV5BMTMyNTYyNzkzMl5BMl5BanBnXkFtZTcwNzUwNzMzMQ@@._V1_SX300.jpg","imdbID":"tt0360005","reviews":[],"createdAt":"2022-05-23T13:53:47.042Z"},{"Title":"Zombi 56: Hopping Mad to the Sound of Music","Year":"1992","Type":"movie","Poster":"https://m.media-amazon.com/images/M/MV5BMGQxOThjN2ItZjdkYS00MTg0LTllNDktYWZiYjQ4ODk4OTViXkEyXkFqcGdeQXVyNzI1NzMxNzM@._V1_SX300.jpg","imdbID":"tt0121906","reviews":[],"createdAt":"2022-05-23T13:53:47.042Z"},{"Title":"The Sound of Music: From Fact to Phenomenon","Year":"1994","Type":"movie","Poster":"https://m.media-amazon.com/images/M/MV5BNTlmNjExNjQtMTNkZC00MzM1LTg3MmQtOWQ5YjIzZGUyNTg4L2ltYWdlXkEyXkFqcGdeQXVyMTY5MDE5NA@@._V1_SX300.jpg","imdbID":"tt0324029","reviews":[],"createdAt":"2022-05-23T13:53:47.042Z"},{"Title":"The Sound of Music","Year":"1996","Type":"movie","Poster":"https://m.media-amazon.com/images/M/MV5BZGU4ZTUwNWUtNzc1Yi00MTAwLWFmYWYtZGQ3YzY5MTViMTM2XkEyXkFqcGdeQXVyNzg5OTk2OA@@._V1_SX300.jpg","imdbID":"tt0813553","reviews":[],"createdAt":"2022-05-23T13:53:47.042Z"},{"Title":"Sound of Cinema: The Music That Made the Movies","Year":"2013","Type":"series","Poster":"https://m.media-amazon.com/images/M/MV5BZDczZDRiNmQtMWQzNi00ODFmLTgwNzEtYmE2YzhlM2Y4MDIwXkEyXkFqcGdeQXVyNjE5NjI4NzI@._V1_SX300.jpg","imdbID":"tt7107400","reviews":[],"createdAt":"2022-05-23T13:53:47.042Z"}]
